taguchi/__init__.py
taguchi/__main__.py
taguchi/database.json
taguchi-1.1.5.dist-info/METADATA
taguchi-1.1.5.dist-info/WHEEL
taguchi-1.1.5.dist-info/entry_points.txt
taguchi-1.1.5.dist-info/top_level.txt
taguchi-1.1.5.dist-info/RECORD
