Metadata-Version: 2.1
Name: taguchi
Version: 1.1.5
Summary: A tool for optimising systems parameterised by environment variables, based on Taguchi/orthogonal array systems of experiments.
Home-page: https://github.com/jcranney/taguchi
Author: Jesse Cranney
Author-email: jesse.cranney@anu.edu.au
License: MIT license
Classifier: Programming Language :: Python :: 3
Requires-Python: >=3.8
